{
    "word": "一匹",
    "tags": [
        "measure"
    ],
    "explanations": [
        {
            "explanation": "一匹",
            "translate": {
                "english": "a horse like animal"
            },
            "examples": [
                {
                    "example": "草原上奔跑着一匹骏马，它的身姿是那么矫健。",
                    "translate": {
                        "english": "A fine horse is running on the grassland, and its posture is so vigorous."
                    }
                },
                {
                    "example": "我骑着一匹白马驰骋在广阔的草原上，感受着自由的气息。",
                    "translate": {
                        "english": "I ride a white horse galloping on the vast prairie, feeling the breath of freedom."
                    }
                },
                {
                    "example": "我在画中描绘了一匹栩栩如生的骏马，仿佛要从画中奔腾而出。",
                    "translate": {
                        "english": "I depicted a vivid and lively horse in the painting, as if it were about to gallop out from the painting."
                    }
                }
            ]
        }
    ]
}