{
    "word": "不够",
    "tags": [
        "hsk2"
    ],
    "explanations": [
        {
            "explanation": "不够",
            "translate": {
                "english": "not enough"
            },
            "examples": [
                {
                    "example": "我觉得自己的努力还不够，还需要更加勤奋才行。",
                    "translate": {
                        "english": "I think my own efforts are not enough, and I still need to be more diligent."
                    }
                },
                {
                    "example": "我觉得自己的知识储备还不够，要继续努力学习才行。",
                    "translate": {
                        "english": "I feel that my knowledge reserve is still not enough, and I have to continue to study hard."
                    }
                },
                {
                    "example": "我觉得自己的经验还不够，要不断积累才行。",
                    "translate": {
                        "english": "I think my experience is still not enough and it is necessary to continuously accumulate."
                    }
                }
            ]
        }
    ]
}