{
    "word": "不用",
    "tags": [
        "hsk1"
    ],
    "explanations": [
        {
            "explanation": "不用",
            "translate": {
                "english": "no need"
            },
            "examples": [
                {
                    "example": "遇到困难不用害怕，勇敢面对就会找到解决办法。",
                    "translate": {
                        "english": "Don't be afraid when encountering difficulties. If you face them bravely, you will find a solution."
                    }
                },
                {
                    "example": "生活中不用过于焦虑，保持平和的心态往往会收获更多美好。",
                    "translate": {
                        "english": "In life, don't be overly anxious, and maintaining a peaceful state of mind often reaps more beauty."
                    }
                },
                {
                    "example": "我们不用过于担心未来，只要努力前行就能创造美好。",
                    "translate": {
                        "english": "We don't need to worry too much about the future. As long as we strive forward, we can create beauty."
                    }
                }
            ]
        }
    ]
}