{
    "word": "便当",
    "tags": [
        "food"
    ],
    "explanations": [
        {
            "explanation": "便当",
            "translate": {
                "english": "lunch box"
            },
            "examples": [
                {
                    "example": "妈妈每天精心准备的便当充满了爱与关怀。",
                    "translate": {
                        "english": "The lunch box carefully prepared by mother every day is full of love and care."
                    }
                },
                {
                    "example": "我为自己准备了一份美味的便当，开启了美好又充实的一天。",
                    "translate": {
                        "english": "I prepared a delicious bento for myself and started a beautiful and fulfilling day."
                    }
                },
                {
                    "example": "他总是带着自制的便当去上班，既健康又环保。",
                    "translate": {
                        "english": "He always takes the homemade lunch box to work, which is both healthy and environmentally friendly."
                    }
                }
            ]
        }
    ]
}