{
    "word": "到处",
    "tags": [
        "hsk2"
    ],
    "explanations": [
        {
            "explanation": "到处",
            "translate": {
                "english": "everywhere"
            },
            "examples": [
                {
                    "example": "春天来了，花园里到处都是盛开的花朵，美丽极了。",
                    "translate": {
                        "english": "Spring has come, and the garden is full of blooming flowers everywhere, extremely beautiful."
                    }
                },
                {
                    "example": "节日的城市到处张灯结彩，充满了欢乐的氛围。",
                    "translate": {
                        "english": "The city during the festival is decorated with lanterns and streamers everywhere, full of a joyful atmosphere."
                    }
                },
                {
                    "example": "阳光明媚的日子里，大自然到处都充满了生机与活力。",
                    "translate": {
                        "english": "On sunny days, nature is full of vigor and vitality everywhere."
                    }
                }
            ]
        }
    ]
}