{
    "word": "小坏蛋",
    "tags": [
        "love"
    ],
    "explanations": [
        {
            "explanation": "小坏蛋",
            "translate": {
                "english": "rascal"
            },
            "examples": [
                {
                    "example": "那个可爱的小坏蛋总是能给大家带来无尽的欢乐。",
                    "translate": {
                        "english": "That cute little rascal can always bring endless joy to everyone."
                    }
                },
                {
                    "example": "他这个有点调皮的小坏蛋其实有着一颗善良热情的心。",
                    "translate": {
                        "english": "He, this somewhat naughty little rascal actually has a kind and passionate heart."
                    }
                },
                {
                    "example": "我的弟弟虽然有时候像个小坏蛋，但他的调皮总能让家里充满欢声笑语。",
                    "translate": {
                        "english": "Although my younger brother is sometimes like a little villain, his naughtiness can always fill the home with laughter and happiness."
                    }
                }
            ]
        }
    ]
}