{
    "word": "帅哥",
    "tags": [
        "love"
    ],
    "explanations": [
        {
            "explanation": "帅哥",
            "translate": {
                "english": "handsome man"
            },
            "examples": [
                {
                    "example": "那位帅哥非常有礼貌，总是微笑着与人打招呼。",
                    "translate": {
                        "english": "That handsome guy is very polite and always greets people with a smile."
                    }
                },
                {
                    "example": "走在路上，那位帅哥热情地帮老奶奶拎东西过马路。",
                    "translate": {
                        "english": "Walking on the road, that handsome guy helped the grandma carry things and cross the road enthusiastically."
                    }
                },
                {
                    "example": "那位帅哥很有爱心，经常去参加志愿者活动。",
                    "translate": {
                        "english": "That handsome guy is very caring and often goes to participate in volunteer activities."
                    }
                }
            ]
        }
    ]
}