{
    "word": "收到",
    "tags": [
        "hsk2"
    ],
    "explanations": [
        {
            "explanation": "收到",
            "translate": {
                "english": "receive / get"
            },
            "examples": [
                {
                    "example": "我很高兴地收到了朋友寄来的礼物。",
                    "translate": {
                        "english": "I am very glad to have received the gift sent by my friend."
                    }
                },
                {
                    "example": "我开心地收到了老师给予的表扬和鼓励。",
                    "translate": {
                        "english": "I happily received the praise and encouragement given by the teacher."
                    }
                },
                {
                    "example": "我收到了远方亲人寄来的温暖祝福，心里满是感动和喜悦。",
                    "translate": {
                        "english": "I received the warm blessings sent by distant relatives, and my heart is full of touch and joy."
                    }
                }
            ]
        }
    ]
}