{
    "word": "那样",
    "tags": [
        "hsk2"
    ],
    "explanations": [
        {
            "explanation": "那样",
            "translate": {
                "english": "like that / in that way / so"
            },
            "examples": [
                {
                    "example": "她总是那样积极乐观地面对生活中的各种挑战。",
                    "translate": {
                        "english": "She always faces all kinds of challenges in life so positively and optimistically."
                    }
                },
                {
                    "example": "他总是那样热情地帮助身边的人。",
                    "translate": {
                        "english": "He always helps people around him so passionately."
                    }
                },
                {
                    "example": "天空是那样的蓝，云朵是那样的白，一切都显得那样美好。",
                    "translate": {
                        "english": "The sky is so blue, the clouds are so white, and everything seems so beautiful."
                    }
                }
            ]
        }
    ]
}